aiattribution/__init__.py
aiattribution/cli.py
aiattribution/models.py
aiattribution/parser.py
aiattribution-0.1.0.dist-info/WHEEL
aiattribution-0.1.0.dist-info/entry_points.txt
aiattribution-0.1.0.dist-info/METADATA
aiattribution-0.1.0.dist-info/RECORD
