Metadata-Version: 2.4
Name: aiattribution
Version: 0.1.0
Summary: A Python utility for creating and interpreting AI Attribution statements
Author: Martin Prpič
Author-email: Martin Prpič <mprpic@redhat.com>
License-Expression: MIT
Requires-Dist: click>=8.3.0
Requires-Dist: questionary>=2.1.1
Requires-Python: >=3.10
Project-URL: Homepage, https://github.com/mprpic/aiattribution
Project-URL: Repository, https://github.com/mprpic/aiattribution
